{
 "issue": "1.5.1",
 "tracks": [
  {
   "animate-begin": "",
   "animate-clear": "no",
   "animate-end": "",
   "background-colour": "",
   "background-image": "",
   "display-show-background": "yes",
   "display-show-text": "no",
   "duration": "",
   "links": "",
   "message-colour": "#ffffff",
   "message-font": "Helvetica 20 bold",
   "message-html-background-colour": "white",
   "message-html-height": "300",
   "message-html-width": "300",
   "message-justify": "left",
   "message-text-location": "",
   "message-text-type": "text",
   "message-x": "",
   "message-y": "",
   "plugin": "",
   "show-control-begin": "",
   "show-control-end": "",
   "text": "You have successfuly triggered a show off a button.\n\nThe show will stop when you release the button.\n\nA more realistic example might play a single audio track or a video and be operated from a lid or a door.",
   "thumbnail": "",
   "title": "Welcome",
   "track-html-background-colour": "white",
   "track-html-height": "300",
   "track-html-width": "300",
   "track-ref": "",
   "track-text": "",
   "track-text-colour": "",
   "track-text-font": "",
   "track-text-justify": "left",
   "track-text-location": "",
   "track-text-type": "plain",
   "track-text-x": "0",
   "track-text-y": "0",
   "type": "message"
  }
 ]
}